collection_framework_taa/__init__.py
collection_framework_taa/cli.py
collection_framework_taa/collect_framework.py
collection_framework_taa/exceptions.py
collection_framework_taa-0.0.3.dist-info/METADATA
collection_framework_taa-0.0.3.dist-info/WHEEL
collection_framework_taa-0.0.3.dist-info/licenses/LICENSE
collection_framework_taa-0.0.3.dist-info/RECORD
