Metadata-Version: 2.1
Name: collection_framework_taa
Version: 0.0.3
Summary: Unique symbols counter
Author-email: Example Author <author@example.com>
License-File: LICENSE
Classifier: License :: OSI Approved :: MIT License
Classifier: Operating System :: OS Independent
Classifier: Programming Language :: Python :: 3
Requires-Python: >=3.10
